cachingutil/__init__.py
cachingutil/_metadata.py
cachingutil/args.py
cachingutil/base_cache.py
cachingutil/base_file_cache.py
cachingutil/binary_file_cache.py
cachingutil/double_cache.py
cachingutil/file_cache.py
cachingutil/json_file_cache.py
cachingutil/memory_cache.py
cachingutil/examples/__init__.py
cachingutil/examples/json_example.py
cachingutil/unittests/__init__.py
cachingutil/unittests/interval_tester.py
cachingutil/unittests/test_file_caching.py
cachingutil/unittests/test_memory_caching.py
cachingutil-1.2.7.dist-info/LICENSE.txt
cachingutil-1.2.7.dist-info/METADATA
cachingutil-1.2.7.dist-info/WHEEL
cachingutil-1.2.7.dist-info/entry_points.txt
cachingutil-1.2.7.dist-info/top_level.txt
cachingutil-1.2.7.dist-info/RECORD
