Metadata-Version: 2.1
Name: cachingutil
Version: 1.2.7
Summary: A collection of caching utilities.
Home-page: https://bitbucket.org/daycoder/cachingutil.git
Author: Hywel Thomas
Author-email: hywel.thomas@mac.com
License: MIT
Download-URL: https://bitbucket.org/daycoder/cachingutil.git/get/1.2.7.tar
Keywords: caching
Platform: UNKNOWN
Classifier: Development Status :: 3 - Alpha
Classifier: Intended Audience :: Developers
Classifier: License :: OSI Approved :: MIT License
Classifier: Programming Language :: Python :: 2
Classifier: Programming Language :: Python :: 2.7
Classifier: Programming Language :: Python :: 3
Classifier: Programming Language :: Python :: 3.6
Classifier: Topic :: Utilities
Requires-Dist: pip (>=18.1)
Requires-Dist: requests (>=2.11.1)
Requires-Dist: timingsutil (>=1.5.0)
Requires-Dist: fdutil (>=1.7.8)
Provides-Extra: test
